Metadata-Version: 2.1
Name: certbot-dns-lightsail
Version: 0.1.0
Summary: Amazon Lightsail DNS Authenticator Plugin for Certbot
Home-page: https://github.com/noi/certbot-dns-lightsail
Author: Nobuki Fujii
License: UNKNOWN
Project-URL: Certbot, https://certbot.eff.org/
Project-URL: Amazon Lightsail, https://aws.amazon.com/lightsail/
Platform: UNKNOWN
Classifier: Programming Language :: Python
Classifier: Programming Language :: Python :: 2
Classifier: Programming Language :: Python :: 2.7
Classifier: Programming Language :: Python :: 3
Classifier: Programming Language :: Python :: 3.6
Classifier: Programming Language :: Python :: 3.7
Classifier: Programming Language :: Python :: 3.8
Classifier: Operating System :: POSIX :: Linux
Classifier: Environment :: Plugins
Classifier: License :: OSI Approved :: MIT License
Requires-Python: >=2.7, !=3.0.*, !=3.1.*, !=3.2.*, !=3.3.*, !=3.4.*, !=3.5.*
Requires-Dist: certbot (>=1.8.0)
Requires-Dist: boto3 (>=1.14.59)
Requires-Dist: zope.interface (>=5.1.0)
Provides-Extra: dev
Requires-Dist: tox ; extra == 'dev'
Requires-Dist: flake8 ; extra == 'dev'
Requires-Dist: flake8-import-order ; extra == 'dev'
Requires-Dist: wheel ; extra == 'dev'
Requires-Dist: twine ; extra == 'dev'
Requires-Dist: mock ; (python_version=="2.7") and extra == 'dev'
Requires-Dist: parsedatetime (==2.5) ; (python_version=="2.7") and extra == 'dev'
